osmcp/__init__.py
osmcp/cli.py
osmcp/client.py
osmcp/providers/__template__.py
osmcp/providers/sbb.py
osmcp/providers/utils.py
osmcp-0.1.8.dist-info/METADATA
osmcp-0.1.8.dist-info/WHEEL
osmcp-0.1.8.dist-info/entry_points.txt
osmcp-0.1.8.dist-info/licenses/LICENSE
osmcp-0.1.8.dist-info/RECORD
