Metadata-Version: 2.3
Name: osmcp
Version: 0.1.8
Summary: Python MCP servers exposing Swiss Open Data to compatible LLM clients.
Requires-Python: >=3.12
Requires-Dist: httpx>=0.28.0
Requires-Dist: mcp>=1.0.0
